tda/__init__.py
tda/auth.py
tda/debug.py
tda/streaming.py
tda/utils.py
tda/version.py
tda/client/__init__.py
tda/client/asynchronous.py
tda/client/base.py
tda/client/synchronous.py
tda/contrib/__init__.py
tda/contrib/orders.py
tda/contrib/util.py
tda/orders/__init__.py
tda/orders/common.py
tda/orders/equities.py
tda/orders/generic.py
tda/orders/options.py
tda/scripts/__init__.py
tda/scripts/get_all_symbols.py
tda/scripts/orders_codegen.py
tda_api-1.6.0.data/scripts/tda-generate-token.py
tda_api-1.6.0.data/scripts/tda-order-codegen.py
tests/__init__.py
tests/auth_test.py
tests/client_test.py
tests/debug_test.py
tests/orders_test.py
tests/streaming_test.py
tests/token_lifecycle_test.py
tests/utils.py
tests/utils_test.py
tests/contrib/__init__.py
tests/contrib/orders_test.py
tests/contrib/util_test.py
tests/orders/__init__.py
tests/orders/common_test.py
tests/orders/generic_test.py
tests/orders/options_test.py
tests/scripts/__init__.py
tests/scripts/orders_codegen_test.py
tda_api-1.6.0.dist-info/LICENSE
tda_api-1.6.0.dist-info/METADATA
tda_api-1.6.0.dist-info/WHEEL
tda_api-1.6.0.dist-info/top_level.txt
tda_api-1.6.0.dist-info/RECORD
