Metadata-Version: 2.1
Name: tda-api
Version: 1.6.0
Summary: An unofficial wrapper around the TD Ameritrade HTTP API.
Home-page: https://github.com/alexgolec/tda-api
Author: Alex Golec
Author-email: bottomless.septic.tank@gmail.com
License: MIT
Project-URL: Documentation, https://tda-api.readthedocs.io/en/latest/
Project-URL: Source, https://github.com/alexgolec/tda-api
Project-URL: Tracker, https://github.com/alexgolec/tda-api/issues
Keywords: finance trading equities bonds options research
Platform: UNKNOWN
Classifier: Programming Language :: Python :: 3
Classifier: License :: OSI Approved :: MIT License
Classifier: Operating System :: OS Independent
Classifier: Intended Audience :: Developers
Classifier: Development Status :: 4 - Beta
Classifier: Natural Language :: English
Classifier: Operating System :: OS Independent
Classifier: Topic :: Office/Business :: Financial :: Investment
Requires-Python: >=3.6
Provides-Extra: dev
License-File: LICENSE
